gcli.py
oh_my_git_agent-1.1.4.dist-info/METADATA
oh_my_git_agent-1.1.4.dist-info/WHEEL
oh_my_git_agent-1.1.4.dist-info/entry_points.txt
oh_my_git_agent-1.1.4.dist-info/licenses/LICENSE
oh_my_git_agent-1.1.4.dist-info/RECORD
