Metadata-Version: 2.4
Name: oh-my-git-agent
Version: 1.1.4
Summary: Git Agent for git operations automation. It will commit file by file on day by day, to make sure you have a commit every day.
License: MIT
License-File: LICENSE
Author: Xueyuan Lin
Author-email: linxy59@mail2.sysu.eud.cn
Classifier: License :: OSI Approved :: MIT License
Classifier: Programming Language :: Python :: 2
Classifier: Programming Language :: Python :: 2.7
Classifier: Programming Language :: Python :: 3
Classifier: Programming Language :: Python :: 3.4
Classifier: Programming Language :: Python :: 3.5
Classifier: Programming Language :: Python :: 3.6
Classifier: Programming Language :: Python :: 3.7
Classifier: Programming Language :: Python :: 3.8
Classifier: Programming Language :: Python :: 3.9
Classifier: Programming Language :: Python :: 3.10
Classifier: Programming Language :: Python :: 3.11
Classifier: Programming Language :: Python :: 3.12
Classifier: Programming Language :: Python :: 3.13
Classifier: Programming Language :: Python :: 3.14
Requires-Dist: GitPython
Requires-Dist: PyYAML
Requires-Dist: loguru
Requires-Dist: openai
Requires-Dist: python-dotenv
Requires-Dist: typer
Project-URL: Homepage, https://github.com/LinXueyuanStdio/GitAgent
